Metadata-Version: 2.4
Name: NlpToolkit-AnnotatedSentence
Version: 1.0.40
Summary: Annotated Sentence Processing Library
Home-page: https://github.com/olcaytaner/AnnotatedSentence-Py
Author: olcaytaner
Author-email: olcaytaner@isikun.edu.tr
License-File: LICENSE
Requires-Dist: NlpToolkit-WordNet
Requires-Dist: NlpToolkit-NamedEntityRecognition
Requires-Dist: NlpToolkit-PropBank
Requires-Dist: NlpToolkit-DependencyParser
Requires-Dist: NlpToolkit-FrameNet
Requires-Dist: NlpToolkit-SentiNet
Dynamic: author
Dynamic: author-email
Dynamic: description
Dynamic: description-content-type
Dynamic: home-page
Dynamic: license-file
Dynamic: requires-dist
Dynamic: summary
